Workbook

Sheet Raw_Data
A1: Reliance Industries Ltd (Consolidated) — Inputs (Screener + Moneycontrol) FY2021–FY2025
A7: Line Item | B7: FY2021 | C7: FY2022 | D7: FY2023 | E7: FY2024 | F7: FY2025
A8: Sales (Rs Cr) | B8: 466307 | C8: 694673 | D8: 876396 | E8: 899041 | F8: 962820
A9: Operating Profit / EBIT (Rs Cr) | B9: 80790 | C9: 108581 | D9: 142318 | E9: 162498 | F9: 165598
A10: Net Profit (Rs Cr) | B10: 53739 | C10: 67845 | D10: 74088 | E10: 79020 | F10: 81309
A11: EPS (Rs) | B11: 38.75 | C11: 44.87 | D11: 49.29 | E11: 51.45 | F11: 51.47
A12: Dividend Payout % | B12: 0.09 | C12: 0.09 | D12: 0.09 | E12: 0.1 | F12: 0.11
A13: Equity Capital (Rs Cr) | B13: 6445 | C13: 6765 | D13: 6765 | E13: 6766 | F13: 13532
A14: Reserves (Rs Cr) | B14: 693727 | C14: 772720 | D14: 709106 | E14: 786715 | F14: 829668
A15: Borrowings (Rs Cr) | B15: 278962 | C15: 319158 | D15: 451664 | E15: 350719 | F15: 374313
A16: Other Liabilities (Rs Cr) | B16: 340931 | C16: 399979 | D16: 438346 | E16: 610848 | F16: 732200
A17: Total Assets (Rs Cr) | B17: 1320065 | C17: 1498622 | D17: 1605882 | E17: 1755048 | F17: 1949713
A18: Cash from Operating Activity / CFO (Rs Cr) | B18: 26958 | C18: 110654 | D18: 115032 | E18: 158788 | F18: 178703
A19: Debtor Days | B19: 15 | C19: 12 | D19: 12 | E19: 13 | F19: 16
... A25: Total Current Liabilities (Rs Cr) — Moneycontrol | B25: 277568 | C25: 308662 | D25: 395744 | E25: 397367 | F25: 453737

Sheet Calculated_Ratios
A1: Calculated Financial Ratios (All computed using Excel formulas)
A4: Liquidity
A5: Ratio | B5: FY2021 | C5: FY2022 | D5: FY2023 | E5: FY2024 | F5: FY2025
A6: Current Ratio = Total Current Assets / Total Current Liabilities | B6: =ROUND(Raw_Data!B22/Raw_Data!B25,2) -> 1.34 | C6: =ROUND(Raw_Data!C22/Raw_Data!C25,2) -> 1.12 | D6: =ROUND(Raw_Data!D22/Raw_Data!D25,2) -> 1.07 | E6: =ROUND(Raw_Data!E22/Raw_Data!E25,2) -> 1.18 | F6: =ROUND(Raw_Data!F22/Raw_Data!F25,2) -> 1.1
A7: Quick Ratio = (Current Assets − Inventories) / Current Liabilities | B7: =ROUND((Raw_Data!B22-Raw_Data!B23)/Raw_Data!B25,2) -> 0.82 | C7: =ROUND((Raw_Data!C22-Raw_Data!C23)/Raw_Data!C25,2) -> 0.63 | D7: =ROUND((Raw_Data!D22-Raw_Data!D23)/Raw_Data!D25,2) -> 0.72 | E7: =ROUND((Raw_Data!E22-Raw_Data!E23)/Raw_Data!E25,2) -> 0.91 | F7: =ROUND((Raw_Data!F22-Raw_Data!F23)/Raw_Data!F25,2) -> 0.92
A8: Cash Ratio = Cash & Cash Equivalents / Current Liabilities | B8: =ROUND(Raw_Data!B24/Raw_Data!B25,2) -> 0.06 | C8: =ROUND(Raw_Data!C24/Raw_Data!C25,2) -> 0.12 | D8: =ROUND(Raw_Data!D24/Raw_Data!D25,2) -> 0.17 | E8: =ROUND(Raw_Data!E24/Raw_Data!E25,2) -> 0.24 | F8: =ROUND(Raw_Data!F24/Raw_Data!F25,2) -> 0.23
A9: Operating Cash Coverage = CFO / Other Liabilities | B9: =ROUND(Raw_Data!B18/Raw_Data!B16,2) -> 0.08 | C9: =ROUND(Raw_Data!C18/Raw_Data!C16,2) -> 0.28 | D9: =ROUND(Raw_Data!D18/Raw_Data!D16,2) -> 0.26 | E9: =ROUND(Raw_Data!E18/Raw_Data!E16,2) -> 0.26 | F9: =ROUND(Raw_Data!F18/Raw_Data!F16,2) -> 0.24
A12: Profitability Ratios
A13: Margins and Returns
A14: Ratio | B14: FY2021 | C14: FY2022 | D14: FY2023 | E14: FY2024 | F14: FY2025
A15: EBIT Margin = EBIT / Sales | B15: =ROUND(Raw_Data!B9/Raw_Data!B8,4) -> 0.1733 | C15: =ROUND(Raw_Data!C9/Raw_Data!C8,4) -> 0.1563 | D15: =ROUND(Raw_Data!D9/Raw_Data!D8,4) -> 0.1624 | E15: =ROUND(Raw_Data!E9/Raw_Data!E8,4) -> 0.1807 | F15: =ROUND(Raw_Data!F9/Raw_Data!F8,4) -> 0.172
A16: Net Profit Margin = Net Profit / Sales | B16: =ROUND(Raw_Data!B10/Raw_Data!B8,4) -> 0.1152 | C16: =ROUND(Raw_Data!C10/Raw_Data!C8,4) -> 0.0977 | D16: =ROUND(Raw_Data!D10/Raw_Data!D8,4) -> 0.0845 | E16: =ROUND(Raw_Data!E10/Raw_Data!E8,4) -> 0.0879 | F16: =ROUND(Raw_Data!F10/Raw_Data!F8,4) -> 0.0844
A17: ROA = Net Profit / Total Assets | B17: =ROUND(Raw_Data!B10/Raw_Data!B17,4) -> 0.0407 | C17: =ROUND(Raw_Data!C10/Raw_Data!C17,4) -> 0.0453 | D17: =ROUND(Raw_Data!D10/Raw_Data!D17,4) -> 0.0461 | E17: =ROUND(Raw_Data!E10/Raw_Data!E17,4) -> 0.045 | F17: =ROUND(Raw_Data!F10/Raw_Data!F17,4) -> 0.0417
A18: ROE = Net Profit / (Equity Capital + Reserves) | B18: =ROUND(Raw_Data!B10/(Raw_Data!B13+Raw_Data!B14),4) -> 0.0768 | C18: =ROUND(Raw_Data!C10/(Raw_Data!C13+Raw_Data!C14),4) -> 0.087 | D18: =ROUND(Raw_Data!D10/(Raw_Data!D13+Raw_Data!D14),4) -> 0.1035 | E18: =ROUND(Raw_Data!E10/(Raw_Data!E13+Raw_Data!E14),4) -> 0.0996 | F18: =ROUND(Raw_Data!F10/(Raw_Data!F13+Raw_Data!F14),4) -> 0.0964
A21: Efficiency Ratios
A22: Turnover and Working Capital Efficiency
A23: Ratio | B23: FY2021 | C23: FY2022 | D23: FY2023 | E23: FY2024 | F23: FY2025
A24: Asset Turnover = Sales / Total Assets | B24: =ROUND(Raw_Data!B8/Raw_Data!B17,2) -> 0.35 | C24: =ROUND(Raw_Data!C8/Raw_Data!C17,2) -> 0.46 | D24: =ROUND(Raw_Data!D8/Raw_Data!D17,2) -> 0.55 | E24: =ROUND(Raw_Data!E8/Raw_Data!E17,2) -> 0.51 | F24: =ROUND(Raw_Data!F8/Raw_Data!F17,2) -> 0.49
A25: Inventory Turnover = 365 / Inventory Days | B25: =ROUND(365/Raw_Data!B20,2) -> 3.58 | C25: =ROUND(365/Raw_Data!C20,2) -> 4.4 | D25: =ROUND(365/Raw_Data!D20,2) -> 4.2 | E25: =ROUND(365/Raw_Data!E20,2) -> 3.84 | F25: =ROUND(365/Raw_Data!F20,2) -> 4.29
A26: Receivables Turnover = 365 / Debtor Days | B26: =ROUND(365/Raw_Data!B19,2) -> 24.33 | C26: =ROUND(365/Raw_Data!C19,2) -> 30.42 | D26: =ROUND(365/Raw_Data!D19,2) -> 30.42 | E26: =ROUND(365/Raw_Data!E19,2) -> 28.08 | F26: =ROUND(365/Raw_Data!F19,2) -> 22.81
A27: DSO (days) | B27: =Raw_Data!B19 -> 15 | C27: =Raw_Data!C19 -> 12 | D27: =Raw_Data!D19 -> 12 | E27: =Raw_Data!E19 -> 13 | F27: =Raw_Data!F19 -> 16
A30: Leverage Ratios
A31: Capital Structure
A32: Ratio | B32: FY2021 | C32: FY2022 | D32: FY2023 | E32: FY2024 | F32: FY2025
A33: Debt Ratio = Borrowings / Total Assets | B33: =ROUND(Raw_Data!B15/Raw_Data!B17,3) -> 0.211 | C33: =ROUND(Raw_Data!C15/Raw_Data!C17,3) -> 0.213 | D33: =ROUND(Raw_Data!D15/Raw_Data!D17,3) -> 0.281 | E33: =ROUND(Raw_Data!E15/Raw_Data!E17,3) -> 0.2 | F33: =ROUND(Raw_Data!F15/Raw_Data!F17,3) -> 0.192
A34: Equity Ratio = (Equity+Reserves) / Total Assets | B34: =ROUND((Raw_Data!B13+Raw_Data!B14)/Raw_Data!B17,3) -> 0.53 | C34: =ROUND((Raw_Data!C13+Raw_Data!C14)/Raw_Data!C17,3) -> 0.52 | D34: =ROUND((Raw_Data!D13+Raw_Data!D14)/Raw_Data!D17,3) -> 0.446 | E34: =ROUND((Raw_Data!E13+Raw_Data!E14)/Raw_Data!E17,3) -> 0.452 | F34: =ROUND((Raw_Data!F13+Raw_Data!F14)/Raw_Data!F17,3) -> 0.432
A35: Debt-to-Equity = Borrowings / (Equity+Reserves) | B35: =ROUND(Raw_Data!B15/(Raw_Data!B13+Raw_Data!B14),3) -> 0.398 | C35: =ROUND(Raw_Data!C15/(Raw_Data!C13+Raw_Data!C14),3) -> 0.409 | D35: =ROUND(Raw_Data!D15/(Raw_Data!D13+Raw_Data!D14),3) -> 0.631 | E35: =ROUND(Raw_Data!E15/(Raw_Data!E13+Raw_Data!E14),3) -> 0.442 | F35: =ROUND(Raw_Data!F15/(Raw_Data!F13+Raw_Data!F14),3) -> 0.444
A38: Market Value Ratios (Indicative — current price basis)
A39: Market Ratios
A40: Ratio | B40: FY2021 | C40: FY2022 | D40: FY2023 | E40: FY2024 | F40: FY2025
A41: P/E = Current Price / EPS | B41: =ROUND(Raw_Data!B4/Raw_Data!B11,2) -> 0 | C41: =ROUND(Raw_Data!B4/Raw_Data!C11,2) -> 0 | D41: =ROUND(Raw_Data!B4/Raw_Data!D11,2) -> 0 | E41: =ROUND(Raw_Data!B4/Raw_Data!E11,2) -> 0 | F41: =ROUND(Raw_Data!B4/Raw_Data!F11,2) -> 0
A42: Dividend Yield (est.) = (Payout% × EPS) / Price | B42: =ROUND((Raw_Data!B12*Raw_Data!B11)/Raw_Data!B4,4) -> #DIV/0! | C42: =ROUND((Raw_Data!C12*Raw_Data!C11)/Raw_Data!B4,4) -> #DIV/0! | D42: =ROUND((Raw_Data!D12*Raw_Data!D11)/Raw_Data!B4,4) -> #DIV/0! | E42: =ROUND((Raw_Data!E12*Raw_Data!E11)/Raw_Data!B4,4) -> #DIV/0! | F42: =ROUND((Raw_Data!F12*Raw_Data!F11)/Raw_Data!B4,4) -> #DIV/0!
A43: BVPS (₹) = (Equity+Reserves) / Shares Outstanding | B43: =ROUND((Raw_Data!B13+Raw_Data!B14)/(Raw_Data!B13/Raw_Data!B5),0) -> #DIV/0! | C43: =ROUND((Raw_Data!C13+Raw_Data!C14)/(Raw_Data!C13/Raw_Data!B5),0) -> #DIV/0! | D43: =ROUND((Raw_Data!D13+Raw_Data!D14)/(Raw_Data!D13/Raw_Data!B5),0) -> #DIV/0! | E43: =ROUND((Raw_Data!E13+Raw_Data!E14)/(Raw_Data!E13/Raw_Data!B5),0) -> #DIV/0! | F43: =ROUND((Raw_Data!F13+Raw_Data!F14)/(Raw_Data!F13/Raw_Data!B5),0) -> #DIV/0!

Sheet PPT_Link_Table
A1: Tables for PPT (all linked to Calculated_Ratios)
A3: Slide 3: Liquidity Ratios
A4: Year | B4: 2021 | C4: 2022 | D4: 2023 | E4: 2024 | F4: 2025
A5: Current Ratio = Total Current Assets / Total Current Liabilities | B5: =Calculated_Ratios!B6 -> 1.34 | C5: =Calculated_Ratios!C6 -> 1.12 | D5: =Calculated_Ratios!D6 -> 1.07 | E5: =Calculated_Ratios!E6 -> 1.18 | F5: =Calculated_Ratios!F6 -> 1.1
A6: Quick Ratio = (Current Assets − Inventories) / Current Liabilities | B6: =Calculated_Ratios!B7 -> 0.82 | C6: =Calculated_Ratios!C7 -> 0.63 | D6: =Calculated_Ratios!D7 -> 0.72 | E6: =Calculated_Ratios!E7 -> 0.91 | F6: =Calculated_Ratios!F7 -> 0.92
A7: Cash Ratio = Cash & Cash Equivalents / Current Liabilities | B7: =Calculated_Ratios!B8 -> 0.06 | C7: =Calculated_Ratios!C8 -> 0.12 | D7: =Calculated_Ratios!D8 -> 0.17 | E7: =Calculated_Ratios!E8 -> 0.24 | F7: =Calculated_Ratios!F8 -> 0.23
A8: Operating Cash Coverage = CFO / Other Liabilities | B8: =Calculated_Ratios!B9 -> 0.08 | C8: =Calculated_Ratios!C9 -> 0.28 | D8: =Calculated_Ratios!D9 -> 0.26 | E8: =Calculated_Ratios!E9 -> 0.26 | F8: =Calculated_Ratios!F9 -> 0.24
A11: Slide 4: Profitability Ratios
A12: Year | B12: 2021 | C12: 2022 | D12: 2023 | E12: 2024 | F12: 2025
A13: EBIT Margin = EBIT / Sales | B13: =Calculated_Ratios!B15 -> 0.1733 | C13: =Calculated_Ratios!C15 -> 0.1563 | D13: =Calculated_Ratios!D15 -> 0.1624 | E13: =Calculated_Ratios!E15 -> 0.1807 | F13: =Calculated_Ratios!F15 -> 0.172
A14: Net Profit Margin = Net Profit / Sales | B14: =Calculated_Ratios!B16 -> 0.1152 | C14: =Calculated_Ratios!C16 -> 0.0977 | D14: =Calculated_Ratios!D16 -> 0.0845 | E14: =Calculated_Ratios!E16 -> 0.0879 | F14: =Calculated_Ratios!F16 -> 0.0844
A15: ROA = Net Profit / Total Assets | B15: =Calculated_Ratios!B17 -> 0.0407 | C15: =Calculated_Ratios!C17 -> 0.0453 | D15: =Calculated_Ratios!D17 -> 0.0461 | E15: =Calculated_Ratios!E17 -> 0.045 | F15: =Calculated_Ratios!F17 -> 0.0417
A16: ROE = Net Profit / (Equity Capital + Reserves) | B16: =Calculated_Ratios!B18 -> 0.0768 | C16: =Calculated_Ratios!C18 -> 0.087 | D16: =Calculated_Ratios!D18 -> 0.1035 | E16: =Calculated_Ratios!E18 -> 0.0996 | F16: =Calculated_Ratios!F18 -> 0.0964
A19: Slide 5: Efficiency Ratios
A20: Year | B20: 2021 | C20: 2022 | D20: 2023 | E20: 2024 | F20: 2025
A21: Asset Turnover = Sales / Total Assets | B21: =Calculated_Ratios!B24 -> 0.35 | C21: =Calculated_Ratios!C24 -> 0.46 | D21: =Calculated_Ratios!D24 -> 0.55 | E21: =Calculated_Ratios!E24 -> 0.51 | F21: =Calculated_Ratios!F24 -> 0.49
A22: Inventory Turnover = 365 / Inventory Days | B22: =Calculated_Ratios!B25 -> 3.58 | C22: =Calculated_Ratios!C25 -> 4.4 | D22: =Calculated_Ratios!D25 -> 4.2 | E22: =Calculated_Ratios!E25 -> 3.84 | F22: =Calculated_Ratios!F25 -> 4.29
A23: Receivables Turnover = 365 / Debtor Days | B23: =Calculated_Ratios!B26 -> 24.33 | C23: =Calculated_Ratios!C26 -> 30.42 | D23: =Calculated_Ratios!D26 -> 30.42 | E23: =Calculated_Ratios!E26 -> 28.08 | F23: =Calculated_Ratios!F26 -> 22.81
A24: DSO (days) | B24: =Calculated_Ratios!B27 -> 15 | C24: =Calculated_Ratios!C27 -> 12 | D24: =Calculated_Ratios!D27 -> 12 | E24: =Calculated_Ratios!E27 -> 13 | F24: =Calculated_Ratios!F27 -> 16
A27: Slide 6: Leverage Ratios
A28: Year | B28: 2021 | C28: 2022 | D28: 2023 | E28: 2024 | F28: 2025
A29: Debt Ratio = Borrowings / Total Assets | B29: =Calculated_Ratios!B33 -> 0.211 | C29: =Calculated_Ratios!C33 -> 0.213 | D29: =Calculated_Ratios!D33 -> 0.281 | E29: =Calculated_Ratios!E33 -> 0.2 | F29: =Calculated_Ratios!F33 -> 0.192
A30: Equity Ratio = (Equity+Reserves) / Total Assets | B30: =Calculated_Ratios!B34 -> 0.53 | C30: =Calculated_Ratios!C34 -> 0.52 | D30: =Calculated_Ratios!D34 -> 0.446 | E30: =Calculated_Ratios!E34 -> 0.452 | F30: =Calculated_Ratios!F34 -> 0.432
A31: Debt-to-Equity = Borrowings / (Equity+Reserves) | B31: =Calculated_Ratios!B35 -> 0.398 | C31: =Calculated_Ratios!C35 -> 0.409 | D31: =Calculated_Ratios!D35 -> 0.631 | E31: =Calculated_Ratios!E35 -> 0.442 | F31: =Calculated_Ratios!F35 -> 0.444
A34: Slide 7: Market Value Ratios
A35: Year | B35: 2021 | C35: 2022 | D35: 2023 | E35: 2024 | F35: 2025
A36: P/E = Current Price / EPS | B36: =Calculated_Ratios!B41 -> 0 | C36: =Calculated_Ratios!C41 -> 0 | D36: =Calculated_Ratios!D41 -> 0 | E36: =Calculated_Ratios!E41 -> 0 | F36: =Calculated_Ratios!F41 -> 0
A37: Dividend Yield (est.) = (Payout% × EPS) / Price | B37: =Calculated_Ratios!B42 -> #DIV/0! | C37: =Calculated_Ratios!C42 -> #DIV/0! | D37: =Calculated_Ratios!D42 -> #DIV/0! | E37: =Calculated_Ratios!E42 -> #DIV/0! | F37: =Calculated_Ratios!F42 -> #DIV/0!
A38: BVPS (₹) = (Equity+Reserves) / Shares Outstanding | B38: =Calculated_Ratios!B43 -> #DIV/0! | C38: =Calculated_Ratios!C43 -> #DIV/0! | D38: =Calculated_Ratios!D43 -> #DIV/0! | E38: =Calculated_Ratios!E43 -> #DIV/0! | F38: =Calculated_Ratios!F43 -> #DIV/0!
